titans_pytorch/__init__.py
titans_pytorch/implicit_mlp_attention.py
titans_pytorch/mac_transformer.py
titans_pytorch/memory_models.py
titans_pytorch/nested_attention.py
titans_pytorch/neural_memory.py
titans_pytorch-0.5.0.dist-info/METADATA
titans_pytorch-0.5.0.dist-info/WHEEL
titans_pytorch-0.5.0.dist-info/licenses/LICENSE
titans_pytorch-0.5.0.dist-info/RECORD
