Metadata-Version: 2.4
Name: titans-pytorch
Version: 0.5.0
Summary: Titans
Project-URL: Homepage, https://pypi.org/project/titans-pytorch/
Project-URL: Repository, https://github.com/lucidrains/titans-pytorch
Author-email: Phil Wang <lucidrains@gmail.com>
License: MIT License
License-File: LICENSE
Keywords: artificial intelligence,deep learning,linear attention,memory,test time training
Classifier: Development Status :: 4 - Beta
Classifier: Intended Audience :: Developers
Classifier: License :: OSI Approved :: MIT License
Classifier: Programming Language :: Python :: 3.9
Classifier: Topic :: Scientific/Engineering :: Artificial Intelligence
Requires-Python: >=3.9
Requires-Dist: assoc-scan>=0.0.4
Requires-Dist: axial-positional-embedding>=0.3.10
Requires-Dist: einops>=0.8.0
Requires-Dist: einx>=0.3.0
Requires-Dist: hyper-connections>=0.3.11
Requires-Dist: ninja
Requires-Dist: rotary-embedding-torch
Requires-Dist: tensordict
Requires-Dist: torch>=2.8
Requires-Dist: tqdm
Requires-Dist: x-transformers
Provides-Extra: examples
Requires-Dist: adam-atan2-pytorch>=0.1.18; extra == 'examples'
Requires-Dist: wandb; extra == 'examples'
Provides-Extra: test
Requires-Dist: pytest; extra == 'test'
